vdutils/__init__.py
vdutils/bjd.py
vdutils/bjdconnector.py
vdutils/convaddr.py
vdutils/cordate.py
vdutils/genpnu.py
vdutils/resources.py
vdutils/vid.py
vdutils/data/__init__.py
vdutils/data/bjd/20230701/bjd.txt
vdutils/data/bjd/20230701/bjd_changed.txt
vdutils/data/bjd/20230701/bjd_current.txt
vdutils/data/bjd/20230701/bjd_frequency_dictionary.txt
vdutils/data/bjd/20230701/bjd_smallest.txt
vdutils/data/bjd/20230701/multiple_word_sgg_list.txt
vdutils/data/bjd/20240118/bjd.txt
vdutils/data/bjd/20240118/bjd_changed.txt
vdutils/data/bjd/20240118/bjd_current.txt
vdutils/data/bjd/20240118/bjd_frequency_dictionary.txt
vdutils/data/bjd/20240118/bjd_smallest.txt
vdutils/data/bjd/20240118/multiple_word_sgg_list.txt
vdutils/data/bjd/20240201/bjd.txt
vdutils/data/bjd/20240201/bjd_changed.txt
vdutils/data/bjd/20240201/bjd_current.txt
vdutils/data/bjd/20240201/bjd_frequency_dictionary.txt
vdutils/data/bjd/20240201/bjd_smallest.txt
vdutils/data/bjd/20240201/multiple_word_sgg_list.txt
vdutils/data/bjd/20240801/bjd.txt
vdutils/data/bjd/20240801/bjd_changed.txt
vdutils/data/bjd/20240801/bjd_current.txt
vdutils/data/bjd/20240801/bjd_frequency_dictionary.txt
vdutils/data/bjd/20240801/bjd_smallest.txt
vdutils/data/bjd/20240801/multiple_word_sgg_list.txt
vdutils/data/bjd/20250513/bjd.txt
vdutils/data/bjd/20250513/bjd_changed.txt
vdutils/data/bjd/20250513/bjd_current.txt
vdutils/data/bjd/20250513/bjd_frequency_dictionary.txt
vdutils/data/bjd/20250513/bjd_smallest.txt
vdutils/data/bjd/20250513/multiple_word_sgg_list.txt
vdutils/data/bjd/20250630/bjd.txt
vdutils/data/bjd/20250630/bjd_changed.txt
vdutils/data/bjd/20250630/bjd_current.txt
vdutils/data/bjd/20250630/bjd_frequency_dictionary.txt
vdutils/data/bjd/20250630/bjd_smallest.txt
vdutils/data/bjd/20250630/multiple_word_sgg_list.txt
vdutils/data/bjd/20251017/bjd.txt
vdutils/data/bjd/20251017/bjd_changed.txt
vdutils/data/bjd/20251017/bjd_current.txt
vdutils/data/bjd/20251017/bjd_frequency_dictionary.txt
vos_data_utils-1.0.12.dist-info/METADATA
vos_data_utils-1.0.12.dist-info/WHEEL
vos_data_utils-1.0.12.dist-info/entry_points.txt
vos_data_utils-1.0.12.dist-info/top_level.txt
vos_data_utils-1.0.12.dist-info/RECORD
