Metadata-Version: 2.1
Name: vos-data-utils
Version: 1.0.12
Summary: description
Author: ValueOfSpace
Author-email: dev@valueofspace.com
Classifier: License :: OSI Approved :: MIT License
Classifier: Operating System :: OS Independent
Classifier: Programming Language :: Python :: 3
Classifier: Programming Language :: Python :: 3.8
Classifier: Programming Language :: Python :: 3.9
Classifier: Programming Language :: Python :: 3.10
Classifier: Programming Language :: Python :: 3.11
Classifier: Programming Language :: Python :: 3.12
Requires-Python: >=3.8
Requires-Dist: symspellpy
Requires-Dist: pandas
Requires-Dist: requests
Requires-Dist: python-dotenv
